{
    "app_id": "e4edc79f0bb6bbe2e7b7dd98b863",
    "collection_id": "eaedc79f0be2eaada8c48199c40e",
    "items": [],
    "name": "Vending_Machine_Inventory",
    "permissions": {
        "Equipment": 5,
        "Maintenance": 15
    },
    "schema": [
        {
            "ColumnName": "item_id",
            "ColumnType": "uuid",
            "PK": true
        },
        {
            "ColumnName": "vending_machine_id",
            "ColumnType": "int",
            "PK": false
        },
        {
            "ColumnName": "slot",
            "ColumnType": "int",
            "PK": false
        },
        {
            "ColumnName": "product_id",
            "ColumnType": "string",
            "PK": false
        },
        {
            "ColumnName": "quantity",
            "ColumnType": "int",
            "PK": false
        }
    ]
}